l18nprint/__init__.py
l18nprint/constants.py
l18nprint/l18nprint.py
l18nprint-0.1.1.dist-info/WHEEL
l18nprint-0.1.1.dist-info/METADATA
l18nprint-0.1.1.dist-info/RECORD
