Metadata-Version: 2.1
Name: l18nprint
Version: 0.1.1
Summary: Python monkey patch wrapper for making print print correctly.
License: MIT
Author: novafacing
Author-email: rowanbhart@gmail.com
Requires-Python: >=3.6.2,<4.0.0
Classifier: License :: OSI Approved :: MIT License
Classifier: Programming Language :: Python :: 3
Classifier: Programming Language :: Python :: 3.7
Classifier: Programming Language :: Python :: 3.8
Classifier: Programming Language :: Python :: 3.9
